k7eel/__init__.py
k7eel/main.py
k7eel2_ss-0.1.1.dist-info/METADATA
k7eel2_ss-0.1.1.dist-info/WHEEL
k7eel2_ss-0.1.1.dist-info/entry_points.txt
k7eel2_ss-0.1.1.dist-info/top_level.txt
k7eel2_ss-0.1.1.dist-info/RECORD
